power_decos/__init__.py
power_decos/_logging_fomatter_json.py
power_decos/cache_decorator.py
power_decos/log_decorator.py
power_decos/retry_decorator.py
power_decos/run_time_decorator.py
power_decos-0.1.5.dist-info/LICENSE.txt
power_decos-0.1.5.dist-info/METADATA
power_decos-0.1.5.dist-info/WHEEL
power_decos-0.1.5.dist-info/RECORD
