Metadata-Version: 2.1
Name: power_decos
Version: 0.1.5
Summary: A python package full of different decorator utils
Home-page: https://mrcode200.github.io/power_decos/
License: MIT
Keywords: decorators,log,retry,get_time,cache
Author: MrCode200
Author-email: navidyaghmaei@gmail.com
Requires-Python: >=3.11,<4.0
Classifier: License :: OSI Approved :: MIT License
Classifier: Programming Language :: Python :: 3
Classifier: Programming Language :: Python :: 3.11
Classifier: Programming Language :: Python :: 3.12
Requires-Dist: platformdirs (>=3.2.0,<4.0.0)
Project-URL: Repository, https://github.com/MrCode200/power_decos
